norfetools.py
norfetools/Bibcleaner.py
norfetools/FileTools.py
norfetools/__init__.py
norfetools/colors.py
norfetools/norfetools.py
norfetool-1.3.5.dist-info/METADATA
norfetool-1.3.5.dist-info/WHEEL
norfetool-1.3.5.dist-info/top_level.txt
norfetool-1.3.5.dist-info/RECORD
