Metadata-Version: 2.1
Name: norfetool
Version: 1.3.5
Summary: Finish Arial Control.Fixed scg fonts!pt refresh!
Home-page: https://github.com/liftes/PythonDraw
Author: norfe
Author-email: 21121598@bjtu.edu.cn
Maintainer: norfe
Maintainer-email: 21121598@bjtu.edu.cn
License: BSD License
Platform: all
Classifier: Development Status :: 4 - Beta
Classifier: Operating System :: OS Independent
Classifier: Intended Audience :: Developers
Classifier: License :: OSI Approved :: BSD License
Classifier: Programming Language :: Python
Classifier: Programming Language :: Python :: Implementation
Classifier: Programming Language :: Python :: 2.7
Classifier: Programming Language :: Python :: 3
Classifier: Programming Language :: Python :: 3.4
Classifier: Programming Language :: Python :: 3.5
Classifier: Programming Language :: Python :: 3.6
Classifier: Programming Language :: Python :: 3.7
Classifier: Programming Language :: Python :: 3.8
Classifier: Programming Language :: Python :: 3.9
Classifier: Programming Language :: Python :: 3.10
Classifier: Programming Language :: Python :: 3.11
Classifier: Topic :: Software Development :: Libraries
Requires-Dist: matplotlib
Requires-Dist: numpy
